recfast4py/DM_annihilation.Recfast.cpp
recfast4py/DM_annihilation.Recfast.h
recfast4py/ODE_solver.Recfast.cpp
recfast4py/ODE_solver.Recfast.h
recfast4py/Rec_corrs_CT.Recfast.cpp
recfast4py/Rec_corrs_CT.Recfast.h
recfast4py/__init__.py
recfast4py/_recfast.cpp
recfast4py/_recfast.cpython-39-darwin.so
recfast4py/_recfast.h
recfast4py/_recfast.pyx
recfast4py/constants.Recfast.h
recfast4py/cosmology.Recfast.cpp
recfast4py/cosmology.Recfast.h
recfast4py/evalode.Recfast.cpp
recfast4py/evalode.Recfast.h
recfast4py/recfast.py
recfast4py/recombination.Recfast.cpp
recfast4py/recombination.Recfast.h
recfast4py/data/DXe_Xe.CT2010.dat
recfast4py-0.3.0.dist-info/licenses/AUTHORS.rst
recfast4py-0.3.0.dist-info/licenses/LICENSE
recfast4py-0.3.0.dist-info/METADATA
recfast4py-0.3.0.dist-info/WHEEL
recfast4py-0.3.0.dist-info/top_level.txt
recfast4py-0.3.0.dist-info/RECORD
